AUTHORS
LICENSE
MANIFEST.in
README.rst
distribute_setup.py
requirements.txt
setup.py
bastio/__init__.py
bastio/account.py
bastio/cli.py
bastio/concurrency.py
bastio/configs.py
bastio/excepts.py
bastio/log.py
bastio/mixin.py
bastio/version.py
bastio/ssh/__init__.py
bastio/ssh/api.py
bastio/ssh/client.py
bastio/ssh/crypto.py
bastio/ssh/protocol.py
bastio/test/__init__.py
bastio/test/test_concurrency.py
bastio/test/test_configs.py
bastio/test/test_mixin.py
bastio/test/test_ssh_api.py
bastio/test/test_ssh_client.py
bastio/test/test_ssh_crypto.py
bastio/test/test_ssh_protocol.py
bastio_agent.egg-info/PKG-INFO
bastio_agent.egg-info/SOURCES.txt
bastio_agent.egg-info/dependency_links.txt
bastio_agent.egg-info/entry_points.txt
bastio_agent.egg-info/requires.txt
bastio_agent.egg-info/top_level.txt