Metadata-Version: 1.1
Name: bastio-agent
Version: 0.1.2
Summary: Bastio agent to provision system accounts and SSH access
Home-page: https://bastio.com
Author: Amr Ali
Author-email: amr@databracket.com
License: GPLv3+
Platform: Posix
Classifier: License :: OSI Approved :: GNU General Public License v3 or later (GPLv3+)
Classifier: Operating System :: OS Independent
Classifier: Programming Language :: Python
Classifier: Natural Language :: English
Classifier: Intended Audience :: Developers
Classifier: Intended Audience :: Information Technology
Classifier: Intended Audience :: System Administrators
Classifier: Topic :: System :: Systems Administration
Classifier: Programming Language :: Python :: 2
Classifier: Programming Language :: Python :: 2.7
